ragbits/guardrails/__init__.py
ragbits/guardrails/base.py
ragbits/guardrails/openai_moderation.py
ragbits/guardrails/py.typed
ragbits_guardrails-1.3.0.dist-info/METADATA
ragbits_guardrails-1.3.0.dist-info/WHEEL
ragbits_guardrails-1.3.0.dist-info/RECORD
