Metadata-Version: 2.4
Name: ragbits-guardrails
Version: 1.3.0
Summary: Guardrails module for Ragbits components
Project-URL: Homepage, https://github.com/deepsense-ai/ragbits
Project-URL: Bug Reports, https://github.com/deepsense-ai/ragbits/issues
Project-URL: Documentation, https://ragbits.deepsense.ai/
Project-URL: Source, https://github.com/deepsense-ai/ragbits
Author-email: "deepsense.ai" <ragbits@deepsense.ai>
License-Expression: MIT
Keywords: Evaluation,GenAI,Generative AI,LLMs,Large Language Models,RAG,Retrieval Augmented Generation
Classifier: Development Status :: 4 - Beta
Classifier: Environment :: Console
Classifier: Intended Audience :: Science/Research
Classifier: License :: OSI Approved :: MIT License
Classifier: Natural Language :: English
Classifier: Operating System :: OS Independent
Classifier: Programming Language :: Python :: 3.10
Classifier: Programming Language :: Python :: 3.11
Classifier: Programming Language :: Python :: 3.12
Classifier: Programming Language :: Python :: 3.13
Classifier: Topic :: Scientific/Engineering :: Artificial Intelligence
Classifier: Topic :: Software Development :: Libraries :: Python Modules
Requires-Python: >=3.10
Requires-Dist: ragbits-core==1.3.0
Provides-Extra: openai
Requires-Dist: openai<2.0.0,>=1.91.0; extra == 'openai'
